tno/mpc/protocols/secure_comparison/__init__.py
tno/mpc/protocols/secure_comparison/communicator.py
tno/mpc/protocols/secure_comparison/initiator.py
tno/mpc/protocols/secure_comparison/keyholder.py
tno/mpc/protocols/secure_comparison/py.typed
tno/mpc/protocols/secure_comparison/utils.py
tno/mpc/protocols/secure_comparison/test/__init__.py
tno/mpc/protocols/secure_comparison/test/conftest.py
tno/mpc/protocols/secure_comparison/test/integration/__init__.py
tno/mpc/protocols/secure_comparison/test/integration/test_pool.py
tno/mpc/protocols/secure_comparison/test/unit/__init__.py
tno/mpc/protocols/secure_comparison/test/unit/test_secure_comparison.py
tno.mpc.protocols.secure_comparison-4.4.0.dist-info/LICENSE
tno.mpc.protocols.secure_comparison-4.4.0.dist-info/METADATA
tno.mpc.protocols.secure_comparison-4.4.0.dist-info/WHEEL
tno.mpc.protocols.secure_comparison-4.4.0.dist-info/top_level.txt
tno.mpc.protocols.secure_comparison-4.4.0.dist-info/RECORD
