Metadata-Version: 2.1
Name: tno.mpc.protocols.secure_comparison
Version: 4.4.0
Summary: Implementation of secure comparison protocol as given in https://eprint.iacr.org/2018/1100.pdf
Author-email: TNO PET Lab <petlab@tno.nl>
Maintainer-email: TNO PET Lab <petlab@tno.nl>
License: Apache License, Version 2.0
Project-URL: Homepage, https://pet.tno.nl/
Project-URL: Documentation, https://docs.pet.tno.nl/mpc/protocols/secure_comparison/4.4.0
Project-URL: Source, https://github.com/TNO-MPC/protocols.secure_comparison
Keywords: TNO,MPC,multi-party computation,protocols,secure comparison
Platform: any
Classifier: License :: OSI Approved :: Apache Software License
Classifier: Programming Language :: Python :: 3
Classifier: Operating System :: OS Independent
Classifier: Intended Audience :: Developers
Classifier: Intended Audience :: Information Technology
Classifier: Intended Audience :: Science/Research
Classifier: Typing :: Typed
Classifier: Topic :: Security :: Cryptography
Requires-Python: >=3.9
License-File: LICENSE
Requires-Dist: tno.mpc.communication~=4.8
Requires-Dist: tno.mpc.encryption_schemes.dgk~=3.0
Requires-Dist: tno.mpc.encryption_schemes.paillier~=3.0
Requires-Dist: tno.mpc.encryption_schemes.templates>=4.1.3,~=4.1
Requires-Dist: tno.mpc.encryption_schemes.utils~=0.10
Provides-Extra: gmpy
Requires-Dist: tno.mpc.encryption_schemes.dgk[gmpy]; extra == "gmpy"
Requires-Dist: tno.mpc.encryption_schemes.paillier[gmpy]; extra == "gmpy"
Provides-Extra: tests
Requires-Dist: pytest>=8.1; extra == "tests"
Requires-Dist: pytest-asyncio; extra == "tests"
